cloud_bucket_adapter/.DS_Store
cloud_bucket_adapter/__init__.py
cloud_bucket_adapter/adapter.py
cloud_bucket_adapter/custom_blob.py
cloud_bucket_adapter/django_adapter.py
cloud_bucket_adapter/aws/__init__.py
cloud_bucket_adapter/aws/adapter.py
cloud_bucket_adapter/gcp/__init__.py
cloud_bucket_adapter/gcp/adapter.py
cloud_bucket_adapter-1.0.1.dist-info/METADATA
cloud_bucket_adapter-1.0.1.dist-info/WHEEL
cloud_bucket_adapter-1.0.1.dist-info/licenses/LICENSE
cloud_bucket_adapter-1.0.1.dist-info/RECORD
