Metadata-Version: 2.1
Name: cloud-bucket-adapter
Version: 1.0.0
Summary: A generic cloud adapter for gcp/aws services to upload/download files on bucket.
Author-email: Gopichand <gopichand.chitirala@fabric.inc>
License: Copyright (c) 2018 The Python Packaging Authority
Project-URL: Homepage, https://github.com/pypa/sampleproject
Project-URL: Bug Tracker, https://github.com/pypa/sampleproject/issues
Classifier: Programming Language :: Python :: 3
Classifier: License :: OSI Approved :: MIT License
Classifier: Operating System :: OS Independent
Requires-Python: >=3.7
License-File: LICENSE
